odoo/addons/check_concurrent_update/README.rst
odoo/addons/check_concurrent_update/__init__.py
odoo/addons/check_concurrent_update/__manifest__.py
odoo/addons/check_concurrent_update/models/__init__.py
odoo/addons/check_concurrent_update/models/base.py
odoo/addons/check_concurrent_update/readme/CONTRIBUTORS.rst
odoo/addons/check_concurrent_update/readme/DESCRIPTION.rst
odoo/addons/check_concurrent_update/readme/INSTALL.rst
odoo/addons/check_concurrent_update/static/description/index.html
odoo/addons/check_concurrent_update/static/src/js/views/basic/basic_model.js
odoo/addons/check_concurrent_update/views/web_assets_backend.xml
odoo_addon_check_concurrent_update-16.0.1.0.0.dist-info/METADATA
odoo_addon_check_concurrent_update-16.0.1.0.0.dist-info/WHEEL
odoo_addon_check_concurrent_update-16.0.1.0.0.dist-info/top_level.txt
odoo_addon_check_concurrent_update-16.0.1.0.0.dist-info/RECORD
